{
  "id": "blog_id",
  "title": "Moj blog 2",
  "authors": [
    {
      "id": "author_10",
      "type": "Entry"
    },
    {
      "id": "author_12",
      "type": "Entry"
    }
  ],
  "posts": [
    {
      "id": "post_1",
      "type": "Entry"
    },
    {
      "id": "post_3",
      "type": "Entry"
    },
    {
      "id": "post_5",
      "type": "Entry"
    },
    {
      "id": "post_9",
      "type": "Entry"
    },
    {
      "id": "post_11",
      "type": "Entry"
    },
    {
      "id": "post_15",
      "type": "Entry"
    },
    {
      "id": "post_21",
      "type": "Entry"
    }
  ],
  "categories": [
    {
      "id": "category_14786",
      "type": "Entry"
    },
    {
      "id": "category_2214351",
      "type": "Entry"
    },
    {
      "id": "category_8076",
      "type": "Entry"
    },
    {
      "id": "category_11599757",
      "type": "Entry"
    }
  ],
  "tags": [
    {
      "id": "tag_2656354",
      "type": "Entry"
    },
    {
      "id": "tag_306830130",
      "type": "Entry"
    }
  ]
}